arkhos/__init__.py
arkhos/arkhos_global.py
arkhos/arkhos_local.py
arkhos/base_handler.py
arkhos/flask_handler.py
arkhos/http.py
arkhos/local_cli.py
arkhos/templates.py
arkhos/urls.py
arkhos/utils.py
arkhos/version.py
arkhos-0.1.2.dist-info/LICENSE.txt
arkhos-0.1.2.dist-info/METADATA
arkhos-0.1.2.dist-info/WHEEL
arkhos-0.1.2.dist-info/entry_points.txt
arkhos-0.1.2.dist-info/top_level.txt
arkhos-0.1.2.dist-info/RECORD
