Metadata-Version: 2.2
Name: arkhos
Version: 0.1.2
Summary: Python framework for deploying small apps
Author-email: Jason Strauss <jason@getarkhos.com>
Project-URL: Homepage, https://getArkhos.com
Project-URL: Repo, https://github.com/arkhosapp/arkhos
Requires-Python: >=3.8
License-File: LICENSE.txt
Requires-Dist: Jinja2==3.1.3
Requires-Dist: requests==2.31.0
Requires-Dist: shellingham==1.5.4
Requires-Dist: typer==0.9.0
Requires-Dist: rich==13.7.0
